{
  "f0": "cluster_22",
  "f1": "cluster_24",
  "f2": "cluster_9",
  "f3": "cluster_14",
  "f4": "cluster_2",
  "f5": "cluster_34",
  "f6": "cluster_8",
  "f7": "cluster_4",
  "f8": "cluster_23",
  "f9": "cluster_33",
  "f10": "cluster_13",
  "f11": "cluster_44",
  "f12": "cluster_36",
  "f13": "cluster_47",
  "f14": "cluster_9",
  "f15": "cluster_34",
  "f16": "cluster_19",
  "f17": "cluster_10",
  "f18": "cluster_25",
  "f19": "cluster_38",
  "f20": "cluster_33",
  "f21": "cluster_47",
  "f22": "cluster_41",
  "f23": "cluster_24",
  "f24": "cluster_7",
  "f25": "cluster_30",
  "f26": "cluster_15",
  "f27": "cluster_5",
  "f28": "cluster_40",
  "f29": "cluster_35",
  "f30": "cluster_10",
  "f31": "cluster_17",
  "f32": "cluster_23",
  "f33": "cluster_22",
  "f34": "cluster_17",
  "f35": "cluster_43",
  "f36": "cluster_6",
  "f37": "cluster_12",
  "f38": "cluster_12",
  "f39": "cluster_33",
  "f40": "cluster_4",
  "f41": "cluster_14",
  "f42": "cluster_36",
  "f43": "cluster_21",
  "f44": "cluster_8",
  "f45": "cluster_24",
  "f46": "cluster_22",
  "f47": "cluster_5",
  "f48": "cluster_18",
  "f49": "cluster_3",
  "f50": "cluster_25",
  "f51": "cluster_15",
  "f52": "cluster_5",
  "f53": "cluster_27",
  "f54": "cluster_29",
  "f55": "cluster_2",
  "f56": "cluster_23",
  "f57": "cluster_7",
  "f58": "cluster_47",
  "f59": "cluster_6",
  "f60": "cluster_13",
  "f61": "cluster_32",
  "f62": "cluster_26",
  "f63": "cluster_38",
  "f64": "cluster_20",
  "f65": "cluster_21",
  "f66": "cluster_11",
  "f67": "cluster_1",
  "f68": "cluster_27",
  "f69": "cluster_7",
  "f70": "cluster_19",
  "f71": "cluster_49",
  "f72": "cluster_7",
  "f73": "cluster_20",
  "f74": "cluster_13",
  "f75": "cluster_4",
  "f76": "cluster_23",
  "f77": "cluster_39",
  "f78": "cluster_46",
  "f79": "cluster_26",
  "f80": "cluster_34",
  "f81": "cluster_6",
  "f82": "cluster_8",
  "f83": "cluster_1",
  "f84": "cluster_5",
  "f85": "cluster_0",
  "f86": "cluster_36",
  "f87": "cluster_24",
  "f88": "cluster_5",
  "f89": "cluster_41",
  "f90": "cluster_5",
  "f91": "cluster_11",
  "f92": "cluster_30",
  "f93": "cluster_0",
  "f94": "cluster_1",
  "f95": "cluster_43",
  "f96": "cluster_41",
  "f97": "cluster_24",
  "f98": "cluster_48",
  "f99": "cluster_48",
  "f100": "cluster_44",
  "f101": "cluster_10",
  "f102": "cluster_1",
  "f103": "cluster_39",
  "f104": "cluster_4",
  "f105": "cluster_22",
  "f106": "cluster_37",
  "f107": "cluster_26",
  "f108": "cluster_43",
  "f109": "cluster_6",
  "f110": "cluster_14",
  "f111": "cluster_16",
  "f112": "cluster_45",
  "f113": "cluster_40",
  "f114": "cluster_50",
  "f115": "cluster_3",
  "f116": "cluster_48",
  "f117": "cluster_6",
  "f118": "cluster_12",
  "f119": "cluster_8",
  "f120": "cluster_3",
  "f121": "cluster_10",
  "f122": "cluster_2",
  "f123": "cluster_43",
  "f124": "cluster_2",
  "f125": "cluster_39",
  "f126": "cluster_9",
  "f127": "cluster_41",
  "f128": "cluster_30",
  "f129": "cluster_37",
  "f130": "cluster_20",
  "f131": "cluster_0",
  "f132": "cluster_11",
  "f133": "cluster_7",
  "f134": "cluster_3",
  "f135": "cluster_1",
  "f136": "cluster_2",
  "f137": "cluster_12",
  "f138": "cluster_3",
  "f139": "cluster_9",
  "f140": "cluster_9",
  "f141": "cluster_3",
  "f142": "cluster_13",
  "f143": "cluster_17",
  "f144": "cluster_26",
  "f145": "cluster_49",
  "f146": "cluster_22",
  "f147": "cluster_13",
  "f148": "cluster_1",
  "f149": "cluster_15",
  "f150": "cluster_32",
  "f151": "cluster_45",
  "f152": "cluster_16",
  "f153": "cluster_8",
  "f154": "cluster_40",
  "f155": "cluster_27",
  "f156": "cluster_18",
  "f157": "cluster_2",
  "f158": "cluster_40",
  "f159": "cluster_34",
  "f160": "cluster_44",
  "f161": "cluster_15",
  "f162": "cluster_51",
  "f163": "cluster_6",
  "f164": "cluster_39",
  "f165": "cluster_19",
  "f166": "cluster_1",
  "f167": "cluster_2",
  "f168": "cluster_18",
  "f169": "cluster_12",
  "f170": "cluster_23",
  "f171": "cluster_47",
  "f172": "cluster_5",
  "f173": "cluster_16",
  "f174": "cluster_25",
  "f175": "cluster_31",
  "f176": "cluster_35",
  "f177": "cluster_11",
  "f178": "cluster_32",
  "f179": "cluster_4",
  "f180": "cluster_7",
  "f181": "cluster_19",
  "f182": "cluster_22",
  "f183": "cluster_6",
  "f184": "cluster_20",
  "f185": "cluster_9",
  "f186": "cluster_35",
  "f187": "cluster_0",
  "f188": "cluster_29",
  "f189": "cluster_23",
  "f190": "cluster_35",
  "f191": "cluster_0",
  "f192": "cluster_5",
  "f193": "cluster_48",
  "f194": "cluster_5",
  "f195": "cluster_31",
  "f196": "cluster_33",
  "f197": "cluster_18",
  "f198": "cluster_16",
  "f199": "cluster_17",
  "f200": "cluster_8",
  "f201": "cluster_32",
  "f202": "cluster_4",
  "f203": "cluster_8",
  "f204": "cluster_9",
  "f205": "cluster_29",
  "f206": "cluster_2",
  "f207": "cluster_10",
  "f208": "cluster_0",
  "f209": "cluster_4",
  "f210": "cluster_11",
  "f211": "cluster_37",
  "f212": "cluster_22",
  "f213": "cluster_30",
  "f214": "cluster_1",
  "f215": "cluster_2",
  "f216": "cluster_13",
  "f217": "cluster_7",
  "f218": "cluster_0",
  "f219": "cluster_42",
  "f220": "cluster_49",
  "f221": "cluster_3",
  "f222": "cluster_12",
  "f223": "cluster_50",
  "f224": "cluster_3",
  "f225": "cluster_12",
  "f226": "cluster_9",
  "f227": "cluster_43",
  "f228": "cluster_50",
  "f229": "cluster_32",
  "f230": "cluster_0",
  "f231": "cluster_4",
  "f232": "cluster_6",
  "f233": "cluster_38",
  "f234": "cluster_8",
  "f235": "cluster_35",
  "f236": "cluster_12",
  "f237": "cluster_9",
  "f238": "cluster_4",
  "f239": "cluster_4",
  "f240": "cluster_1",
  "f241": "cluster_28",
  "f242": "cluster_27",
  "f243": "cluster_0",
  "f244": "cluster_20",
  "f245": "cluster_7",
  "f246": "cluster_27",
  "f247": "cluster_38",
  "f248": "cluster_23",
  "f249": "cluster_20",
  "f250": "cluster_0",
  "f251": "cluster_4",
  "f252": "cluster_8",
  "f253": "cluster_46",
  "f254": "cluster_46",
  "f255": "cluster_11",
  "f256": "cluster_17",
  "f257": "cluster_6",
  "f258": "cluster_14",
  "f259": "cluster_10",
  "f260": "cluster_19",
  "f261": "cluster_0",
  "f262": "cluster_3",
  "f263": "cluster_16",
  "f264": "cluster_2",
  "f265": "cluster_12",
  "f266": "cluster_1",
  "f267": "cluster_11",
  "f268": "cluster_35",
  "f269": "cluster_28",
  "f270": "cluster_38",
  "f271": "cluster_1",
  "f272": "cluster_37",
  "f273": "cluster_21",
  "f274": "cluster_2",
  "f275": "cluster_45",
  "f276": "cluster_36",
  "f277": "cluster_19",
  "f278": "cluster_18",
  "f279": "cluster_28",
  "f280": "cluster_34",
  "f281": "cluster_5",
  "f282": "cluster_15",
  "f283": "cluster_49",
  "f284": "cluster_11",
  "f285": "cluster_14",
  "f286": "cluster_18",
  "f287": "cluster_9",
  "f288": "cluster_31",
  "f289": "cluster_28",
  "f290": "cluster_30",
  "f291": "cluster_8",
  "f292": "cluster_5",
  "f293": "cluster_25",
  "f294": "cluster_20",
  "f295": "cluster_26",
  "f296": "cluster_46",
  "f297": "cluster_7",
  "f298": "cluster_30",
  "f299": "cluster_11",
  "f300": "cluster_25",
  "f301": "cluster_31",
  "f302": "cluster_3",
  "f303": "cluster_21",
  "f304": "cluster_3",
  "f305": "cluster_41",
  "f306": "cluster_4",
  "f307": "cluster_6",
  "f308": "cluster_21",
  "f309": "cluster_7",
  "f310": "cluster_18",
  "f311": "cluster_14",
  "f312": "cluster_42",
  "f313": "cluster_16",
  "f314": "cluster_26",
  "f315": "cluster_16",
  "f316": "cluster_24",
  "f317": "cluster_5",
  "f318": "cluster_14",
  "f319": "cluster_17",
  "f320": "cluster_0",
  "f321": "cluster_42",
  "f322": "cluster_27",
  "f323": "cluster_16",
  "f324": "cluster_33",
  "f325": "cluster_21",
  "f326": "cluster_31",
  "f327": "cluster_33",
  "f328": "cluster_21",
  "f329": "cluster_0",
  "f330": "cluster_13",
  "f331": "cluster_27",
  "f332": "cluster_14",
  "f333": "cluster_40",
  "f334": "cluster_30",
  "f335": "cluster_32",
  "f336": "cluster_51",
  "f337": "cluster_20",
  "f338": "cluster_28",
  "f339": "cluster_7",
  "f340": "cluster_10",
  "f341": "cluster_42",
  "f342": "cluster_36",
  "f343": "cluster_15",
  "f344": "cluster_10",
  "f345": "cluster_44",
  "f346": "cluster_15",
  "f347": "cluster_1",
  "f348": "cluster_19",
  "f349": "cluster_6",
  "f350": "cluster_39",
  "f351": "cluster_14",
  "f352": "cluster_28",
  "f353": "cluster_29",
  "f354": "cluster_13",
  "f355": "cluster_51",
  "f356": "cluster_29",
  "f357": "cluster_25",
  "f358": "cluster_37",
  "f359": "cluster_10",
  "f360": "cluster_29",
  "f361": "cluster_31",
  "f362": "cluster_19",
  "f363": "cluster_13",
  "f364": "cluster_1",
  "f365": "cluster_25",
  "f366": "cluster_15",
  "f367": "cluster_28",
  "f368": "cluster_2",
  "f369": "cluster_17",
  "f370": "cluster_10",
  "f371": "cluster_18",
  "f372": "cluster_26",
  "f373": "cluster_29",
  "f374": "cluster_34",
  "f375": "cluster_45",
  "f376": "cluster_17",
  "f377": "cluster_44",
  "f378": "cluster_11",
  "f379": "cluster_2",
  "f380": "cluster_3",
  "f381": "cluster_24",
  "f382": "cluster_8",
  "f383": "cluster_42"
}